MANIFEST.in
README.rst
setup.py
collective/__init__.py
collective.portlet.contentleadimage.egg-info/PKG-INFO
collective.portlet.contentleadimage.egg-info/SOURCES.txt
collective.portlet.contentleadimage.egg-info/dependency_links.txt
collective.portlet.contentleadimage.egg-info/entry_points.txt
collective.portlet.contentleadimage.egg-info/namespace_packages.txt
collective.portlet.contentleadimage.egg-info/not-zip-safe
collective.portlet.contentleadimage.egg-info/requires.txt
collective.portlet.contentleadimage.egg-info/top_level.txt
collective/portlet/__init__.py
collective/portlet/contentleadimage/__init__.py
collective/portlet/contentleadimage/configure.zcml
collective/portlet/contentleadimage/contentleadimagecollectionportlet.pt
collective/portlet/contentleadimage/contentleadimagecollectionportlet.py
collective/portlet/contentleadimage/version.txt
collective/portlet/contentleadimage/locales/collective.portlet.contentleadimage.pot
collective/portlet/contentleadimage/locales/plone.pot
collective/portlet/contentleadimage/locales/zcml.pot
collective/portlet/contentleadimage/locales/en/LC_MESSAGES/collective.portlet.contentleadimage.po
collective/portlet/contentleadimage/locales/en/LC_MESSAGES/plone.po
collective/portlet/contentleadimage/locales/es/LC_MESSAGES/collective.portlet.contentleadimage.po
collective/portlet/contentleadimage/locales/es/LC_MESSAGES/plone.po
collective/portlet/contentleadimage/locales/eu/LC_MESSAGES/collective.portlet.contentleadimage.po
collective/portlet/contentleadimage/locales/eu/LC_MESSAGES/plone.po
collective/portlet/contentleadimage/profiles/default/metadata.xml
collective/portlet/contentleadimage/profiles/default/portlets.xml
collective/portlet/contentleadimage/tests/__init__.py
collective/portlet/contentleadimage/tests/base.py
collective/portlet/contentleadimage/tests/test_41x41.jpg
collective/portlet/contentleadimage/tests/test_portlet.py
docs/HISTORY.txt
docs/INSTALL.txt
docs/LICENSE.GPL
docs/LICENSE.txt