Metadata-Version: 1.1
Name: collective.portlet.contentleadimage
Version: 0.5.1
Summary: Collection portlet that shows contenteleadimages
Home-page: http://github.com/collective/collective.portlet.contentleadimage
Author: Ales Zabala Alava (Shagi)
Author-email: shagi@gisa-elkartea.org
License: GPL
Platform: UNKNOWN
Classifier: Framework :: Plone
Classifier: Programming Language :: Python
Classifier: Development Status :: 4 - Beta
Classifier: License :: OSI Approved :: GNU General Public License (GPL)
